string_clean_util/__init__.py
string_clean_util/string_clean_util.py
string_clean_util-1.7.dist-info/METADATA
string_clean_util-1.7.dist-info/WHEEL
string_clean_util-1.7.dist-info/top_level.txt
string_clean_util-1.7.dist-info/RECORD
