Metadata-Version: 2.1
Name: string_clean_util
Version: 1.7
Summary: A library that cleans up common string artifacts from strings
Home-page: 
Author: JB-102
